LICENSE
MANIFEST.in
README.rst
setup.py
ascii_graph/__init__.py
ascii_graph/colordata.py
ascii_graph/colors.py
ascii_graph.egg-info/PKG-INFO
ascii_graph.egg-info/SOURCES.txt
ascii_graph.egg-info/dependency_links.txt
ascii_graph.egg-info/top_level.txt
docs/Makefile
docs/ascii_graph.rst
docs/changelog.rst
docs/colordata.rst
docs/colors.rst
docs/conf.py
docs/examples.rst
docs/index.rst
docs/make.bat
docs/requirements.txt
examples/color_graphs.py
examples/color_multivalue_graphs.py
examples/gdu.sh
examples/graphs.py
examples/human_readable.py
examples/loadtop.sh
examples/with_utf8.py
scripts/asciigraph
tests/test_lib.py
tests/__pycache__/test_lib.cpython-27-PYTEST.pyc