Metadata-Version: 1.1
Name: ascii-graph
Version: 1.1.4
Summary: A simple python lib to print data as ascii histograms.
Home-page: https://github.com/kakwa/py-ascii-graph
Author: Pierre-Francois Carpentier
Author-email: carpentier.pf@gmail.com
License: Copyright (c) 2012 Pierre-Francois Carpentier <carpentier.pf@gmail.com> 
